ramannoodle/__init__.py
ramannoodle/abstract.py
ramannoodle/constants.py
ramannoodle/exceptions.py
ramannoodle/dataset/__init__.py
ramannoodle/dataset/torch/__init__.py
ramannoodle/dataset/torch/_dataset.py
ramannoodle/dataset/torch/utils.py
ramannoodle/dynamics/__init__.py
ramannoodle/dynamics/_phonon.py
ramannoodle/dynamics/_trajectory.py
ramannoodle/io/__init__.py
ramannoodle/io/_utils.py
ramannoodle/io/generic.py
ramannoodle/io/pymatgen.py
ramannoodle/io/vasp/__init__.py
ramannoodle/io/vasp/outcar.py
ramannoodle/io/vasp/poscar.py
ramannoodle/io/vasp/vasprun.py
ramannoodle/io/vasp/xdatcar.py
ramannoodle/pmodel/__init__.py
ramannoodle/pmodel/_art.py
ramannoodle/pmodel/_interpolation.py
ramannoodle/pmodel/torch/__init__.py
ramannoodle/pmodel/torch/_gnn.py
ramannoodle/pmodel/torch/_train.py
ramannoodle/pmodel/torch/_utils.py
ramannoodle/spectrum/__init__.py
ramannoodle/spectrum/_raman.py
ramannoodle/spectrum/utils.py
ramannoodle/structure/__init__.py
ramannoodle/structure/_displace.py
ramannoodle/structure/_reference.py
ramannoodle/structure/_symmetry_utils.py
ramannoodle/structure/utils.py
ramannoodle-0.5.0.dist-info/LICENSE.txt
ramannoodle-0.5.0.dist-info/METADATA
ramannoodle-0.5.0.dist-info/WHEEL
ramannoodle-0.5.0.dist-info/top_level.txt
ramannoodle-0.5.0.dist-info/RECORD
