Metadata-Version: 2.1
Name: ramannoodle
Version: 0.5.0
Summary: Calculate Raman spectra from first-principles calculations.
Author-email: Willis O'Leary <wolearyc@gmail.com>
License: MIT
Project-URL: Documentation, https://ramannoodle.readthedocs.io/en/latest/
Project-URL: Repository, https://github.com/wolearyc/ramannoodle
Project-URL: Issues, https://github.com/wolearyc/ramannoodle/issues
Keywords: raman,spectrum,vasp,dft,phonons,molecular,dynamics,polarizability
Requires-Python: >=3.10
License-File: LICENSE.txt
Requires-Dist: defusedxml >=0.6.0
Requires-Dist: spglib >=1.16.4
Requires-Dist: tabulate >=0.8.8
Requires-Dist: tqdm >=2.0
Requires-Dist: numpy >=1.24.0 ; python_version == "3.10"
Requires-Dist: scipy >=1.10.0 ; python_version == "3.10"
Requires-Dist: numpy >=1.24.0 ; python_version == "3.11"
Requires-Dist: scipy >=1.10.0 ; python_version == "3.11"
Requires-Dist: numpy >=1.26.0 ; python_version == "3.12"
Requires-Dist: scipy >=1.11.2 ; python_version == "3.12"
Provides-Extra: pymatgen
Requires-Dist: matplotlib >=3.7.0 ; extra == 'pymatgen'
Requires-Dist: mpmath >=1.2.0 ; extra == 'pymatgen'
Requires-Dist: pandas >=2.0.0 ; extra == 'pymatgen'
Requires-Dist: pymatgen >=2024.8.9 ; extra == 'pymatgen'
Requires-Dist: pyparsing >=3.0.0 ; extra == 'pymatgen'
Requires-Dist: ruamel-yaml >=0.17.2 ; extra == 'pymatgen'
Requires-Dist: uncertainties >=3.1.7 ; extra == 'pymatgen'
Requires-Dist: pillow >=8.3.2 ; (python_version == "3.10" and sys_platform == "darwin") and extra == 'pymatgen'
Requires-Dist: pillow >=8.3.2 ; (python_version == "3.10" and sys_platform == "linux") and extra == 'pymatgen'
Requires-Dist: pillow >=8.3.2 ; (python_version == "3.10" and sys_platform == "win32") and extra == 'pymatgen'
Requires-Dist: pillow >=8.3.2 ; (python_version == "3.11" and sys_platform == "darwin") and extra == 'pymatgen'
Requires-Dist: pillow >=8.3.2 ; (python_version == "3.11" and sys_platform == "linux") and extra == 'pymatgen'
Requires-Dist: pillow >=10.0.0 ; (python_version == "3.11" and sys_platform == "win32") and extra == 'pymatgen'
Requires-Dist: sympy >=1.13.3 ; (python_version == "3.12") and extra == 'pymatgen'
Requires-Dist: pillow >=10.1.0 ; (python_version == "3.12" and sys_platform == "darwin") and extra == 'pymatgen'
Requires-Dist: pillow >=10.1.0 ; (python_version == "3.12" and sys_platform == "linux") and extra == 'pymatgen'
Requires-Dist: pillow >=10.1.0 ; (python_version == "3.12" and sys_platform == "win32") and extra == 'pymatgen'
Provides-Extra: torch
Requires-Dist: dill >=0.3.4 ; extra == 'torch'
Requires-Dist: fsspec >=2021.4.0 ; extra == 'torch'
Requires-Dist: jinja2 >=3.0.2 ; extra == 'torch'
Requires-Dist: pyparsing >=3.0.0 ; extra == 'torch'
Requires-Dist: torch-geometric >=2.3.0 ; extra == 'torch'
Requires-Dist: aiohttp >=3.8.0 ; (python_version == "3.10") and extra == 'torch'
Requires-Dist: frozenlist >=1.2.0 ; (python_version == "3.10") and extra == 'torch'
Requires-Dist: scikit-learn >=1.2.0 ; (python_version == "3.10") and extra == 'torch'
Requires-Dist: aiohttp >=3.8.3 ; (python_version == "3.11") and extra == 'torch'
Requires-Dist: frozenlist >=1.3.3 ; (python_version == "3.11") and extra == 'torch'
Requires-Dist: scikit-learn >=1.2.0 ; (python_version == "3.11") and extra == 'torch'
Requires-Dist: aiohttp >=3.9.0 ; (python_version == "3.12") and extra == 'torch'
Requires-Dist: frozenlist >=1.4.1 ; (python_version == "3.12") and extra == 'torch'
Requires-Dist: scikit-learn >=1.3.0 ; (python_version == "3.12" and sys_platform == "darwin") and extra == 'torch'
Requires-Dist: scikit-learn >=1.3.0 ; (python_version == "3.12" and sys_platform == "linux") and extra == 'torch'
Requires-Dist: scikit-learn >=1.4.0 ; (python_version == "3.12" and sys_platform == "win32") and extra == 'torch'
